README.md
setup.cfg
setup.py
bin/masstodon
bin/masstodon_trial
bin/plotly_spectrum
masstodon/__init__.py
masstodon/masstodon.py
masstodon.egg-info/PKG-INFO
masstodon.egg-info/SOURCES.txt
masstodon.egg-info/dependency_links.txt
masstodon.egg-info/requires.txt
masstodon.egg-info/top_level.txt
masstodon/amino_acid/aminoAcid.py
masstodon/arrays/__init__.py
masstodon/arrays/aggregations.py
masstodon/arrays/operations.py
masstodon/data/__init__.py
masstodon/data/amino_acids.py
masstodon/data/constants.py
masstodon/data/dummy.py
masstodon/data/elements.py
masstodon/data/get_dataset.py
masstodon/data/isotopes.py
masstodon/data/ptms.py
masstodon/data/substanceP_wh15_wv400.py
masstodon/data/substance_p.py
masstodon/data/substance_p_wv_1_5_wh_4500.py
masstodon/deconvolve/__init__.py
masstodon/deconvolve/deconvolve.py
masstodon/deconvolve/divide_ed_impera.py
masstodon/deconvolve/test_deconvolve.py
masstodon/deconvolve/test_groups.py
masstodon/estimates_matcher/__init__.py
masstodon/estimates_matcher/cz.py
masstodon/estimates_matcher/cz_simple.py
masstodon/estimates_matcher/test_cz.py
masstodon/formula/__init__.py
masstodon/formula/formula.py
masstodon/formula/linear_dict.py
masstodon/formula/parse.py
masstodon/isotopes/__init__.py
masstodon/isotopes/calculator.py
masstodon/isotopes/envelope.py
masstodon/isotopes/isospec.py
masstodon/isotopes/misc.py
masstodon/isotopes/test_calculator.py
masstodon/measure/__init__.py
masstodon/measure/measure.py
masstodon/misc/__init__.py
masstodon/misc/strings.py
masstodon/models/__init__.py
masstodon/models/denoiser.py
masstodon/models/model.py
masstodon/models/nnls.py
masstodon/models/polynomial.py
masstodon/models/quantile_deconvolution.py
masstodon/models/spline.py
masstodon/models/two_dimensional.py
masstodon/molecule/__init__.py
masstodon/molecule/molecule.py
masstodon/ome/__init__.py
masstodon/ome/ome.py
masstodon/parse/__init__.py
masstodon/parse/blocked_fragments.py
masstodon/parse/mods.py
masstodon/parse/mzml.py
masstodon/parse/npy.py
masstodon/parse/output.py
masstodon/parse/path.py
masstodon/parse/spectrum.py
masstodon/parse/spectrum_file.py
masstodon/parse/threshold.py
masstodon/parse/txt.py
